LICENSE.txt
MANIFEST.in
setup.cfg
setup.py
paom/__init__.py
paom/base.py
paom/client.py
paom.egg-info/PKG-INFO
paom.egg-info/SOURCES.txt
paom.egg-info/dependency_links.txt
paom.egg-info/requires.txt
paom.egg-info/top_level.txt
paom/resources/__init__.py
paom/resources/orders.py
paom/resources/products.py
paom/resources/quizzes.py
paom/resources/users.py