Metadata-Version: 1.1
Name: paom
Version: 0.5.4
Summary: API integration of PAOM
Home-page: https://bitbucket.org/msrobot0/paom_python_api
Author: Meredith Finkelstein Chang
Author-email: meredith@printallover.me
License: MIT
Download-URL: https://bitbucket.org/msrobot0/paom_python_api/tarball/0.3
Keywords: paom,python,paom api
Platform: UNKNOWN
